roUtilities/__init__.py
roUtilities/roUtils.py
roUtilities-0.1.2.dist-info/LICENSE
roUtilities-0.1.2.dist-info/METADATA
roUtilities-0.1.2.dist-info/WHEEL
roUtilities-0.1.2.dist-info/top_level.txt
roUtilities-0.1.2.dist-info/RECORD
