Metadata-Version: 2.1
Name: roUtilities
Version: 0.1.2
Summary: Adds an utilities, that rorosin needs in his projects.
Home-page: https://github.com/Anton-Rosin-Dev/roUtilities/
Author: rorosin
License: MIT License        
Project-URL: Homepage, https://github.com/Anton-Rosin-Dev/roUtilities/
Project-URL: Bug Tracker, https://github.com/Anton-Rosin-Dev/roUtilities/issues
Classifier: Programming Language :: Python :: 3
Classifier: License :: OSI Approved :: MIT License
Classifier: Operating System :: OS Independent
Requires-Python: >=3.7
License-File: LICENSE
Requires-Dist: colorama (>=0.4.5)
